a11y_checker/__init__.py
a11y_checker/client.py
a11y_checker-1.0.4.dist-info/licenses/LICENSE
a11y_checker-1.0.4.dist-info/METADATA
a11y_checker-1.0.4.dist-info/WHEEL
a11y_checker-1.0.4.dist-info/top_level.txt
a11y_checker-1.0.4.dist-info/RECORD
