Metadata-Version: 2.4
Name: a11y-checker
Version: 1.0.4
Summary: Asynchronous Python client for the accessibility checker API
Author-email: Jacek Labudda <j.labudda@dock.codes>
License-Expression: MIT
Keywords: accessibility,audit,scan,test,async
Requires-Python: >=3.9
License-File: LICENSE
Requires-Dist: aiohttp>=3.9
Dynamic: license-file
